[
    {
        "image": "guitarra_electrica_yamaha_pacifica_012_dark.jpg"
    },
    {
        "image": "81WrWq-bKTL._AC_SX679_.jpg"
    },
    {
        "image": "340333000-1-300x300.jpg"
    },
    {
        "image": "D_821154-MLA42066070556_062020-F-600x288.jpg"
    },
    {
        "image": "D_NQ_NP_674442-MLA46543861330_062021-O.JPEG"
    },
    {
        "image": "1410171854593622_01_medium.jpg"
    },
    {
        "image": "GuitarraElectrica.jpg"
    },
    {
        "image": "D_NQ_NP_625727-MLA46364642352_062021-F.jpg"
    },
    {
        "image": "D_NQ_NP_2X_910187-MLA48762610667_012022-F.jpg"
    },
    {
        "image": "D_NQ_NP_2X_636157-MLA50024611111_052022-F(1).jpg"
    },
    {
        "image": "D_NQ_NP_2X_907196-MLA43642239581_102020-F(1).jpg"
    },
    {
        "image": "D_NQ_NP_720076-MLA44038833575_112020-O(1).jpg"
    },
    {
        "image": "D_NQ_NP_2X_951992-MLA49272663857_032022-F.jpg"
    },
    {
        "image": "Img-1665419510064.webp"
    },
    {
        "image": "Img-1665419653864.webp"
    },
    {
        "image": "Img-1665419103755.webp"
    },
    {
        "image": "D_NQ_NP_738608-MLA44112471285_112020-O.webp"
    },
    {
        "image": "Img-1665546092440.webp"
    },
    {
        "image": "Img-1665545839011.webp"
    },
    {
        "image": "D_NQ_NP_2X_975559-MLA32542990330_102019-F.webp"
    },
    {
        "image": "Img-1665580720784.webp"
    },
    {
        "image": "Img-1665580911181.webp"
    },
    {
        "image": "Img-1665581257171.webp"
    },
    {
        "image": "Img-1665581841238.webp"
    },
    {
        "image": "Img-1663006720912.jpg"
    },
    {
        "image": "Img-1665582301229.webp"
    },
    {
        "image": "Img-1665582466134.webp"
    },
    {
        "image": "Img-1665582722713.webp"
    },
    {
        "image": "D_NQ_NP_917263-MLA41662325703_052020-F.jpg"
    },
    {
        "image": "Img-1665589306414.webp"
    },
    {
        "image": "Img-1662932198273.jpg"
    }
]